vikdatashift/__init__.py
vikdatashift/csv_to_db.py
vikdatashift/db_to_csv.py
vikdatashift/db_to_db.py
vikdatashift/main.py
vikdatashift/oracle_to_postgres.py
vikdatashift-1.0.1.dist-info/METADATA
vikdatashift-1.0.1.dist-info/WHEEL
vikdatashift-1.0.1.dist-info/top_level.txt
vikdatashift-1.0.1.dist-info/RECORD
