Metadata-Version: 2.4
Name: vikdatashift
Version: 1.0.1
Requires-Dist: psycopg2>=2.8.0
Requires-Dist: cx_Oracle>=7.0.0
Dynamic: description
Dynamic: description-content-type
Dynamic: requires-dist
